.DS_Store
todo/__init__.py
todo/commandline.py
todo/todo.py
FNEtodo-0.1.1.dist-info/LICENSE.txt
FNEtodo-0.1.1.dist-info/METADATA
FNEtodo-0.1.1.dist-info/WHEEL
FNEtodo-0.1.1.dist-info/entry_points.txt
FNEtodo-0.1.1.dist-info/top_level.txt
FNEtodo-0.1.1.dist-info/RECORD
