Metadata-Version: 2.1
Name: FNEtodo
Version: 0.1.1
Summary: Simple command-line Todo app.
Home-page: https://github.com/FatmanurEraslan/Todo1
Author: Fatmanur Eraslan
Author-email: fatmanur13.fe@gmail.com
License: MIT
Keywords: todo task
Platform: UNKNOWN
Classifier: Development Status :: 3 - Alpha
Classifier: License :: OSI Approved :: MIT License
Classifier: Programming Language :: Python :: 3.6
Classifier: Topic :: Text Processing :: General
